setup.py
bin/blockstack-file
blockstack_file/__init__.py
blockstack_file/blockstack_file.py
blockstack_file/version.py
blockstack_file.egg-info/PKG-INFO
blockstack_file.egg-info/SOURCES.txt
blockstack_file.egg-info/dependency_links.txt
blockstack_file.egg-info/not-zip-safe
blockstack_file.egg-info/requires.txt
blockstack_file.egg-info/top_level.txt