Metadata-Version: 1.1
Name: blockstack-file
Version: 0.14.0
Summary: Blockstack encrypted file sharing
Home-page: https://github.com/blockstack/blockstack-file
Author: Blockstack.org
Author-email: support@blockstack.org
License: GPLv3
Download-URL: https://github.com/blockstack/blockstack-file/archive/master.zip
Keywords: blockchain git crypography name key value store data
Platform: UNKNOWN
Classifier: Intended Audience :: Developers
Classifier: License :: OSI Approved :: GNU General Public License v3 (GPLv3)
Classifier: Operating System :: OS Independent
Classifier: Programming Language :: Python
Classifier: Topic :: Internet
Classifier: Topic :: Security :: Cryptography
Classifier: Topic :: Software Development :: Libraries :: Python Modules
